scriptblocks/App.py
scriptblocks/Button.py
scriptblocks/Node.py
scriptblocks/Scene.py
scriptblocks/Sound.py
scriptblocks/Sprite.py
scriptblocks/Transition.py
scriptblocks/__init__.py
scriptblocks/cli.py
scriptblocks-0.1.0.dist-info/METADATA
scriptblocks-0.1.0.dist-info/WHEEL
scriptblocks-0.1.0.dist-info/entry_points.txt
scriptblocks-0.1.0.dist-info/top_level.txt
scriptblocks-0.1.0.dist-info/RECORD
