Metadata-Version: 2.1
Name: scriptblocks
Version: 0.1.0
Summary: Package used by ScriptBlocks IDE to make apps with Python
Home-page: https://github.com/ScriptBlocks/ScriptBlocks.py
Author: OmgRod
Classifier: Programming Language :: Python :: 3
Classifier: License :: OSI Approved :: MIT License
Classifier: Operating System :: OS Independent
Requires-Python: >=3.6
